[
	
	

	{
		"start": -6000000,
		"label": "Humans",
		"article":"humans.txt",
		"background": [255, 255, 255],
		"accent": [202, 79, 63, 255],
		"asset": 
		{
			"source": "humans.flr",
			"width": 1068,
			"height": 670,
			"offset": 0,
			"bounds":[-534,-670,1602,670],
			"idle":["human_1", "human_2", "human_3", "human_4", "human_5"]
		},
		"ticks": 
		{
			"background": [245, 245, 245, 240],
			"long": [0, 0, 0, 60],
			"short": [0, 0, 0, 35],
			"text": [0, 0, 0, 110]
		},
		"header": 
		{
			"background": [245, 245, 245, 240],
			"text": [0, 0, 0, 110]
		}
	},
	{
		"date": 1997,
		"label": "Day i was born",
		"accent": [115, 132, 205, 255],
		"article":"birthday.txt",
		"asset": 
		{
			"source": "Birth_date/childbirth.png",
			"width": 300,
			"height": 300,
			"offset": 100
		}
	},
	{
		"date": 2003.5,
		"label": "My First school day",
		"accent": [115, 132, 205, 255],
		"article":"birthday.txt",
		
		"asset": 
		{
			"source": "Birth_date/school.png",
			"width": 256,
			"height": 256,
			"offset": 100
		}
	},
	{
		"date": 2018,
		"label": "Graduation day",
		"accent": [115, 132, 205, 255],
		
		"article":"birthday.txt",
		"asset": 
		{
			"source": "Birth_date/student.png",
			"width": 256,
			"height": 256,
			"offset": 100
		}
	}
]